xmllens/__init__.py
xmllens/core.py
xmllens/py.typed
xmllens-0.1.3.dist-info/licenses/LICENSE
xmllens-0.1.3.dist-info/METADATA
xmllens-0.1.3.dist-info/WHEEL
xmllens-0.1.3.dist-info/top_level.txt
xmllens-0.1.3.dist-info/RECORD
