Metadata-Version: 2.4
Name: xmllens
Version: 0.1.3
Summary: A lightweight library to compare XML documents with tolerance and ignore rules.
Author-email: Mohamed Tahri <simotahri1@gmail.com>
License: Apache-2.0
Keywords: xml,diff,compare,tolerance,ignore,xpath
Classifier: Development Status :: 3 - Alpha
Classifier: Intended Audience :: Developers
Classifier: Topic :: Software Development :: Libraries
Classifier: Programming Language :: Python :: 3
Classifier: Programming Language :: Python :: 3.9
Classifier: Programming Language :: Python :: 3.10
Classifier: Programming Language :: Python :: 3.11
Classifier: Programming Language :: Python :: 3.12
Classifier: License :: OSI Approved :: Apache Software License
Requires-Python: >=3.9
License-File: LICENSE
Dynamic: license-file
